protobuf_to_dict.py
protobuf_to_dict_whl-0.1.4.dist-info/LICENSE
protobuf_to_dict_whl-0.1.4.dist-info/METADATA
protobuf_to_dict_whl-0.1.4.dist-info/WHEEL
protobuf_to_dict_whl-0.1.4.dist-info/top_level.txt
protobuf_to_dict_whl-0.1.4.dist-info/RECORD
