Metadata-Version: 2.1
Name: protobuf-to-dict-whl
Version: 0.1.4
Summary: A teeny Python library for creating Python dicts from protocol buffers and the reverse. Useful as an intermediate step before serialisation (e.g. to JSON).  Added support for class metadata
Home-page: https://github.com/surfnerd/protobuf-to-dict
Author: Ben Hodgson with additions by Chris Goy
Author-email: goyenator@gmail.com
License: Public Domain
Keywords: protobuf,json,dict
Platform: UNKNOWN
Classifier: Programming Language :: Python
Classifier: Development Status :: 4 - Beta
Classifier: Intended Audience :: Developers
Classifier: License :: Public Domain
Classifier: Operating System :: OS Independent
Classifier: Topic :: Software Development :: Libraries :: Python Modules
Requires-Dist: protobuf (==3.6.1)
